{
    "key": "group_5ec2d7c2a9cbe",
    "title": "Catalogue Page Customization",
    "fields": [
        {
            "key": "field_5ec2d7c2b531c",
            "label": "Landing",
            "name": "",
            "type": "tab",
            "instructions": "",
            "required": 0,
            "conditional_logic": 0,
            "wrapper": {
                "width": "",
                "class": "",
                "id": ""
            },
            "placement": "top",
            "endpoint": 0
        },
        {
            "key": "field_5ec2d7c2b5337",
            "label": "Section 1 Header Customization",
            "name": "section_1_header_customization",
            "type": "clone",
            "instructions": "",
            "required": 0,
            "conditional_logic": 0,
            "wrapper": {
                "width": "",
                "class": "",
                "id": ""
            },
            "clone": [
                "group_5e7cdd41997c4"
            ],
            "display": "group",
            "layout": "block",
            "prefix_label": 0,
            "prefix_name": 1
        },
        {
            "key": "field_5ec2d7c2b534b",
            "label": "Section 1",
            "name": "section_1",
            "type": "clone",
            "instructions": "",
            "required": 0,
            "conditional_logic": 0,
            "wrapper": {
                "width": "",
                "class": "",
                "id": ""
            },
            "clone": [
                "group_5e6938346ff62"
            ],
            "display": "seamless",
            "layout": "block",
            "prefix_label": 0,
            "prefix_name": 1
        }
    ],
    "location": [
        [
            {
                "param": "page_type",
                "operator": "==",
                "value": "posts_page"
            }
        ]
    ],
    "menu_order": 10,
    "position": "normal",
    "style": "default",
    "label_placement": "top",
    "instruction_placement": "label",
    "hide_on_screen": "",
    "active": 1,
    "description": "",
    "modified": 1589827594
}